Workbook

Sheet Simulacao
B2: Evenflow — simulação financeira do evento
B3: Preencha apenas as células em amarelo. Todo o resto é calculado.
B5: 1. DADOS DO EVENTO
B6: Nome do evento | C6: Exemplo: Festa da Virada
B7: Meta / capacidade de ingressos | C7: 600
B8: Preço médio do ingresso | C8: 65
B10: 2. TAXAS
B11: Taxa de plataforma — Evenflow | C11: 0.08 | F11: Conferida no checkout da Evenflow (PLATFORM_FEE_RATE = 0,08) em 14/09/2026. Sem piso mínimo por ingresso.
B12: Taxa de processamento — Evenflow | C12: 0 | F12: Hoje não há taxa de processamento cobrada por fora. Confirmar com o responsável financeiro.
B13: Taxa de plataforma — concorrente | C13: 0.1 | F13: Exemplo: Sympla, 10% para eventos pagos (mín. R$ 3,99 em ingressos até R$ 39,90). Consultado em 14/09/2026. Troque pelo concorrente real do produtor.
B14: Taxa de processamento — concorrente | C14: 0.0225 | F14: Sympla publica 2% a 2,5%; usado 2,25%. ATENÇÃO: a Central de Ajuda da Sympla descreve o processamento como pago pelo COMPRADOR. Se o produtor repassa a taxa, zere esta célula antes de comparar.
B16: 3. RESULTADO | C16: Evenflow | D16: Concorrente
B17: Receita bruta (ingressos × preço médio) | C17: =C7*C8 -> 39000 | D17: =C7*C8 -> 39000
B18: Custo total da plataforma | C18: =C17*(C11+C12) -> 3120 | D18: =D17*(C13+C14) -> 4777.5
B19: Receita do produtor — taxa absorvida por ele | C19: =C17-C18 -> 35880 | D19: =D17-D18 -> 34222.5
B20: Receita do produtor — taxa repassada ao comprador | C20: =C17 -> 39000 | D20: =D17 -> 39000
B21: Preço final para o comprador — taxa repassada | C21: =C8*(1+C11+C12) -> 70.2 | D21: =C8*(1+C13+C14) -> 72.9625
B23: DIFERENÇA DE CUSTO NO EVENTO (concorrente − Evenflow) | C23: =D18-C18 -> 1657.5
B24: Diferença por ingresso vendido | C24: =IFERROR(C23/C7,0) -> 2.7625
B26: Como ler este número
B27: Positivo: o cenário comparado custaria mais ao evento do que a Evenflow.
B28: Negativo: o cenário comparado custaria menos. Diga isso ao produtor e leve a conversa para operação e acompanhamento.
B29: O cálculo não inclui tributos, tarifas de saque, parcelamento nem antecipação. É estimativa de custo, não garantia de resultado.
B30: Piso por ingresso não entra nesta conta. Em ingresso barato ele muda tudo: um piso de R$ 3,99 num ingresso de R$ 30 equivale a 13,3%.
B31: Antes de usar: pergunte se o produtor absorve ou repassa a taxa hoje. Se ele repassa, o custo dele na plataforma atual pode ser perto de zero.
B33: Legenda: células amarelas = preencher. Texto azul = valor digitado. Texto preto = fórmula.

Sheet Lotes
B2: Receita por lote
B3: Preencha nome, quantidade e preço de cada lote. As três últimas colunas são calculadas.
B5: Lote | C5: Quantidade | D5: Preço | E5: Receita bruta | F5: Taxa Evenflow | G5: Receita líquida
B6: Promocional | C6: 50 | D6: 45 | E6: =IF(C6="","",C6*D6) -> 2250 | F6: =IF(E6="","",E6*Simulacao!$C$11) -> 180 | G6: =IF(E6="","",E6-F6) -> 2070
B7: 1º Lote | C7: 130 | D7: 55 | E7: =IF(C7="","",C7*D7) -> 7150 | F7: =IF(E7="","",E7*Simulacao!$C$11) -> 572 | G7: =IF(E7="","",E7-F7) -> 6578
B8: 2º Lote | C8: 170 | D8: 66 | E8: =IF(C8="","",C8*D8) -> 11220 | F8: =IF(E8="","",E8*Simulacao!$C$11) -> 897.6 | G8: =IF(E8="","",E8-F8) -> 10322.4
B9: 3º Lote | C9: 150 | D9: 75 | E9: =IF(C9="","",C9*D9) -> 11250 | F9: =IF(E9="","",E9*Simulacao!$C$11) -> 900 | G9: =IF(E9="","",E9-F9) -> 10350
B10: Última oportunidade | C10: 100 | D10: 90 | E10: =IF(C10="","",C10*D10) -> 9000 | F10: =IF(E10="","",E10*Simulacao!$C$11) -> 720 | G10: =IF(E10="","",E10-F10) -> 8280
E11: =IF(C11="","",C11*D11) | F11: =IF(E11="","",E11*Simulacao!$C$11) | G11: =IF(E11="","",E11-F11)
E12: =IF(C12="","",C12*D12) | F12: =IF(E12="","",E12*Simulacao!$C$11) | G12: =IF(E12="","",E12-F12)
E13: =IF(C13="","",C13*D13) | F13: =IF(E13="","",E13*Simulacao!$C$11) | G13: =IF(E13="","",E13-F13)
E14: =IF(C14="","",C14*D14) | F14: =IF(E14="","",E14*Simulacao!$C$11) | G14: =IF(E14="","",E14-F14)
E15: =IF(C15="","",C15*D15) | F15: =IF(E15="","",E15*Simulacao!$C$11) | G15: =IF(E15="","",E15-F15)
B16: Total | C16: =SUM(C6:C15) -> 600 | E16: =SUM(E6:E15) -> 40870 | F16: =SUM(F6:F15) -> 3269.6 | G16: =SUM(G6:G15) -> 37600.4
B18: Preço médio ponderado | C18: =IFERROR(E16/C16,0) -> 68.116667
B19: Use este preço médio na aba Simulacao.
B21: Os lotes preenchidos são um exemplo de formato. Substitua pelos lotes reais do evento do produtor.
